discord/ext/helpers/__init__.py
discord/ext/helpers/prefix.py
discord_ext_helpers-1.0.0.dist-info/WHEEL
discord_ext_helpers-1.0.0.dist-info/METADATA
discord_ext_helpers-1.0.0.dist-info/RECORD
